garastem/__init__ copy.py
garastem/__init__.py
garastem/modules.py
garastem/version.py
garastem-0.1683603186.0.dist-info/METADATA
garastem-0.1683603186.0.dist-info/WHEEL
garastem-0.1683603186.0.dist-info/top_level.txt
garastem-0.1683603186.0.dist-info/RECORD
